{
  "package_edges": [
    [
      "analysis",
      "calibration"
    ],
    [
      "analysis",
      "core"
    ],
    [
      "analysis",
      "experiments"
    ],
    [
      "autotune",
      "experiments"
    ],
    [
      "autotune",
      "programs"
    ],
    [
      "calibration",
      "analysis"
    ],
    [
      "calibration",
      "core"
    ],
    [
      "calibration",
      "hardware"
    ],
    [
      "calibration",
      "programs"
    ],
    [
      "compile",
      "gates"
    ],
    [
      "core",
      "analysis"
    ],
    [
      "core",
      "experiments"
    ],
    [
      "core",
      "hardware"
    ],
    [
      "core",
      "programs"
    ],
    [
      "core",
      "pulses"
    ],
    [
      "devices",
      "core"
    ],
    [
      "examples",
      "core"
    ],
    [
      "examples",
      "programs"
    ],
    [
      "examples",
      "pulses"
    ],
    [
      "examples",
      "verification"
    ],
    [
      "experiments",
      "analysis"
    ],
    [
      "experiments",
      "calibration"
    ],
    [
      "experiments",
      "core"
    ],
    [
      "experiments",
      "devices"
    ],
    [
      "experiments",
      "hardware"
    ],
    [
      "experiments",
      "programs"
    ],
    [
      "experiments",
      "pulses"
    ],
    [
      "experiments",
      "tools"
    ],
    [
      "gates",
      "analysis"
    ],
    [
      "gates",
      "core"
    ],
    [
      "hardware",
      "analysis"
    ],
    [
      "hardware",
      "calibration"
    ],
    [
      "hardware",
      "core"
    ],
    [
      "hardware",
      "programs"
    ],
    [
      "programs",
      "analysis"
    ],
    [
      "programs",
      "core"
    ],
    [
      "programs",
      "experiments"
    ],
    [
      "programs",
      "gates"
    ],
    [
      "programs",
      "pulses"
    ],
    [
      "programs",
      "tools"
    ],
    [
      "pulses",
      "analysis"
    ],
    [
      "pulses",
      "core"
    ],
    [
      "pulses",
      "tools"
    ],
    [
      "tests",
      "analysis"
    ],
    [
      "tests",
      "calibration"
    ],
    [
      "tests",
      "experiments"
    ],
    [
      "tests",
      "programs"
    ],
    [
      "tools",
      "core"
    ],
    [
      "tools",
      "pulses"
    ],
    [
      "verification",
      "core"
    ],
    [
      "verification",
      "pulses"
    ]
  ],
  "file_count_per_pkg": {
    "analysis": 16,
    "autotune": 2,
    "calibration": 11,
    "compile": 11,
    "core": 17,
    "devices": 4,
    "examples": 3,
    "experiments": 30,
    "gates": 23,
    "gui": 2,
    "hardware": 6,
    "migration": 1,
    "optimization": 4,
    "programs": 28,
    "pulses": 8,
    "simulation": 5,
    "tests": 5,
    "tools": 3,
    "verification": 4
  },
  "external_deps": [
    "",
    "IPython",
    "PyQt5",
    "__future__",
    "abc",
    "argparse",
    "base64",
    "cma",
    "collections",
    "concurrent",
    "contextlib",
    "copy",
    "cupy",
    "cupyx",
    "dataclasses",
    "datetime",
    "enum",
    "functools",
    "grpclib",
    "hashlib",
    "importlib",
    "inspect",
    "instrumentserver",
    "jax",
    "json",
    "logging",
    "math",
    "matplotlib",
    "mpl_toolkits",
    "numbers",
    "numpy",
    "octave_sdk",
    "os",
    "pandas",
    "pathlib",
    "plotly",
    "pprint",
    "pydantic",
    "pyqtgraph",
    "pytest",
    "qcodes",
    "qm",
    "qualang_tools",
    "qutip",
    "random",
    "re",
    "scipy",
    "shutil",
    "skopt",
    "subprocess",
    "sys",
    "tempfile",
    "threading",
    "time",
    "tqdm",
    "traceback",
    "types",
    "typing",
    "warnings",
    "yaml"
  ]
}